prompeteer/__init__.py
prompeteer/prompeteer.py
prompeteer/prompt/__init__.py
prompeteer/prompt/prompt.py
prompeteer/prompt/prompt_config.py
prompeteer/providers/__init__.py
prompeteer/providers/llm_client.py
prompeteer/providers/llm_request.py
prompeteer/providers/aws_bedrock/__init__.py
prompeteer/providers/aws_bedrock/aws_bedrock_client.py
prompeteer/providers/aws_bedrock/aws_llm_request.py
prompeteer/providers/azure_openai/__init__.py
prompeteer/providers/azure_openai/azure_llm_request.py
prompeteer/providers/azure_openai/azure_openai_client.py
prompeteer/utils/__init__.py
prompeteer/utils/utils.py
prompeteer-0.3.6.dist-info/METADATA
prompeteer-0.3.6.dist-info/WHEEL
prompeteer-0.3.6.dist-info/top_level.txt
prompeteer-0.3.6.dist-info/RECORD
