Metadata-Version: 2.1
Name: prompeteer
Version: 0.3.6
Summary: Prompt Development and Evaluation tool
Author: Yoaz Menda
Author-email: yoazmenda@gmail.com
Classifier: Programming Language :: Python :: 3
Classifier: License :: OSI Approved :: MIT License
Classifier: Operating System :: OS Independent
Requires-Dist: pyyaml
Requires-Dist: openai ==1.28.1
Requires-Dist: azure-identity
Requires-Dist: boto3
Requires-Dist: tenacity
